cechmate/__init__.py
cechmate/_version.py
cechmate/solver.py
cechmate/utils.py
cechmate/filtrations/__init__.py
cechmate/filtrations/alpha.py
cechmate/filtrations/base.py
cechmate/filtrations/cech.py
cechmate/filtrations/custom.py
cechmate/filtrations/extended.py
cechmate/filtrations/miniball.py
cechmate/filtrations/rips.py
test/__init__.py
test/test_alpha.py
test/test_cech.py
test/test_extended.py
test/test_filtrations.py
test/test_miniball.py
test/test_rips.py
test/test_solver.py
test/test_utils.py
cechmate-0.1.0.dist-info/LICENSE
cechmate-0.1.0.dist-info/METADATA
cechmate-0.1.0.dist-info/WHEEL
cechmate-0.1.0.dist-info/top_level.txt
cechmate-0.1.0.dist-info/RECORD
