Metadata-Version: 2.1
Name: cechmate
Version: 0.1.0
Summary: Custom filtration constructors for Python
Home-page: https://cechmate.scikit-tda.org
Author: Christopher Tralie, Nathaniel Saul
Author-email: chris.tralie@gmail.com, nat@saulgill.com
License: MIT
Keywords: persistent homology,persistence images,persistence diagrams,topology data analysis,algebraic topology,unsupervised learning,filtrations,Cech,Alpha,Rips
Platform: UNKNOWN
Classifier: Development Status :: 3 - Alpha
Classifier: Intended Audience :: Science/Research
Classifier: Intended Audience :: Education
Classifier: Intended Audience :: Financial and Insurance Industry
Classifier: Intended Audience :: Healthcare Industry
Classifier: Topic :: Scientific/Engineering :: Information Analysis
Classifier: Topic :: Scientific/Engineering :: Mathematics
Classifier: License :: OSI Approved :: MIT License
Classifier: Programming Language :: Python :: 3.6
Classifier: Programming Language :: Python :: 3.7
Classifier: Programming Language :: Python :: 3.8
Requires-Python: >=3.6
Requires-Dist: scipy
Requires-Dist: numpy
Requires-Dist: matplotlib
Requires-Dist: phat (==1.5.0a0)
Requires-Dist: persim
Provides-Extra: docs
Requires-Dist: sktda-docs-config ; extra == 'docs'
Provides-Extra: testing
Requires-Dist: pytest-cov ; extra == 'testing'
Requires-Dist: mock ; extra == 'testing'
Requires-Dist: kmapper ; extra == 'testing'
Requires-Dist: networkx ; extra == 'testing'
